{
    "activedeveloperbadge": "You can put emoji id manually or follow my intructions",
    "hypesquadbriliance": "You can put emoji id manually or follow my intructions",
    "hypesquadbravery": "You can put emoji id manually or follow my intructions",
    "hypesquadbalance": "You can put emoji id manually or follow my intructions",
    "tlauncher": "You can put emoji id manually or follow my intructions",
    "premium": "You can put emoji id manually or follow my intructions",
    "papercraft": "You can put emoji id manually or follow my intructions",
    "xbox": "You can put emoji id manually or follow my intructions",
    "welcome": "You can put emoji id manually or follow my intructions",
    "warrior": "You can put emoji id manually or follow my intructions",
    "veteran": "You can put emoji id manually or follow my intructions",
    "topGG": "You can put emoji id manually or follow my intructions",
    "skinstealer": "You can put emoji id manually or follow my intructions",
    "skin": "You can put emoji id manually or follow my intructions",
    "rope": "You can put emoji id manually or follow my intructions",
    "roblox": "You can put emoji id manually or follow my intructions",
    "rbxm": "You can put emoji id manually or follow my intructions",
    "minecraft": "You can put emoji id manually or follow my intructions",
    "inviter": "You can put emoji id manually or follow my intructions",
    "IHZAQSTORM33heademoji": "You can put emoji id manually or follow my intructions",
    "homestead": "You can put emoji id manually or follow my intructions",
    "head": "You can put emoji id manually or follow my intructions",
    "gamerscore": "You can put emoji id manually or follow my intructions",
    "funtools": "You can put emoji id manually or follow my intructions",
    "friendship": "You can put emoji id manually or follow my intructions",
    "discordlist": "You can put emoji id manually or follow my intructions",
    "discordbotsgg": "You can put emoji id manually or follow my intructions",
    "discordbotlab": "You can put emoji id manually or follow my intructions",
    "dbl": "You can put emoji id manually or follow my intructions",
    "combat": "You can put emoji id manually or follow my intructions",
    "bricksmith": "You can put emoji id manually or follow my intructions",
    "body": "You can put emoji id manually or follow my intructions",
    "bloxxer": "You can put emoji id manually or follow my intructions",
    "avatar": "You can put emoji id manually or follow my intructions",
    "admin": "You can put emoji id manually or follow my intructions",
    "bot_verified": "You can put emoji id manually or follow my intructions",
    "bot_noverified": "You can put emoji id manually or follow my intructions"
}